nsq_api/__init__.py
nsq_api/service.py
nsq_api-0.0.2.dist-info/METADATA
nsq_api-0.0.2.dist-info/WHEEL
nsq_api-0.0.2.dist-info/dependency_links.txt
nsq_api-0.0.2.dist-info/entry_points.txt
nsq_api-0.0.2.dist-info/top_level.txt
nsq_api-0.0.2.dist-info/RECORD
